clinical_benchmarks/__init__.py
clinical_benchmarks/__main__.py
clinical_benchmarks/clean.py
clinical_benchmarks/data.py
clinical_benchmarks/evaluate.py
clinical_benchmarks/extract.py
clinical_benchmarks/hope.py
clinical_benchmarks/merge.py
clinical_benchmarks/model.py
clinical_benchmarks/preprocess.py
clinical_benchmarks/task.py
clinical_benchmarks/transform.py
clinical_benchmarks/utils.py
clinical_benchmarks/query/__init__.py
clinical_benchmarks/query/mimic/__init__.py
clinical_benchmarks/query/mimic/cohort.sql
clinical_benchmarks/query/mimic/cohort_first_day.sql
clinical_benchmarks/query/mimic/donor_patients.sql
clinical_benchmarks/query/mimic/feature/__init__.py
clinical_benchmarks/query/mimic/feature/chemistry.sql
clinical_benchmarks/query/mimic/feature/coagulation.sql
clinical_benchmarks/query/mimic/feature/complete_blood_count.sql
clinical_benchmarks/query/mimic/feature/height.sql
clinical_benchmarks/query/mimic/feature/vitalsign.sql
clinical_benchmarks/query/mimic/feature/weight.sql
clinical_benchmarks/query/mimic/outcome/__init__.py
clinical_benchmarks/query/mimic/outcome/dialysis.sql
clinical_benchmarks/query/mimic/outcome/heparin_dose.sql
clinical_benchmarks/query/mimic/outcome/inv_vent.sql
clinical_benchmarks/query/mimic/outcome/labevents.sql
clinical_benchmarks/query/mimic/outcome/los_icu.sql
clinical_benchmarks/query/mimic/outcome/mortality.sql
clinical_benchmarks/query/mimic/outcome/vancomycin_dose.sql
clinical_benchmarks/query/mimic/outcome/vancomycin_level.sql
clinical_benchmarks/query/mimic/task_cohort/__init__.py
clinical_benchmarks/query/mimic/task_cohort/heparin_cohort.sql
clinical_benchmarks/query/mimic/task_cohort/vancomycin_cohort.sql
clinical_benchmarks-1.0.0.dist-info/LICENSE
clinical_benchmarks-1.0.0.dist-info/METADATA
clinical_benchmarks-1.0.0.dist-info/WHEEL
clinical_benchmarks-1.0.0.dist-info/entry_points.txt
clinical_benchmarks-1.0.0.dist-info/top_level.txt
clinical_benchmarks-1.0.0.dist-info/RECORD
