Metadata-Version: 2.1
Name: clinical-benchmarks
Version: 1.0.0
Summary: A repo of clinical benchmarks for MIMIC-IV
Home-page: https://github.com/kind-lab/clinical-benchmarks
Author: Alex Bennett, Pengcheng Wang
Author-email: alexmbennett2@gmail.com, cheng666999@gmail.com
Classifier: Programming Language :: Python :: 3
Classifier: Operating System :: OS Independent
Requires-Python: >=3.6
License-File: LICENSE
